{
  "meta": {
    "projet": "pest",
    "schema": "universal-graph-extractor v3.0",
    "langages": {
      "json": 1,
      "php": 118,
      "xml": 1
    }
  },
  "stats": {
    "fichiers_total": 120,
    "edges_total": 36,
    "edges_circulaires": 0,
    "noeuds_centraux": 0,
    "noeuds_feuilles": 3,
    "noeuds_hubs": 0,
    "points_entree": 6,
    "fichier_plus_appele": "src/Support/Closure.php"
  },
  "noeuds": {
    "composer.json": {
      "fichier": "composer.json",
      "langage": "json",
      "lignes": 128,
      "taille_bytes": 4038,
      "entrees": [],
      "sorties": [],
      "appelle": [],
      "est_appele_par": [],
      "type_noeud": "standard"
    },
    "tests-external/Features/Expect/toMatchSnapshot.php": {
      "fichier": "tests-external/Features/Expect/toMatchSnapshot.php",
      "langage": "php",
      "lignes": 35,
      "taille_bytes": 1216,
      "entrees": [
        "Pest\\TestSuite"
      ],
      "sorties": [],
      "appelle": [],
      "est_appele_par": [],
      "type_noeud": "standard"
    },
    "resources/base-phpunit.xml": {
      "fichier": "resources/base-phpunit.xml",
      "langage": "xml",
      "lignes": 31,
      "taille_bytes": 1124,
      "entrees": [],
      "sorties": [],
      "appelle": [],
      "est_appele_par": [],
      "type_noeud": "standard"
    },
    "resources/views/version.php": {
      "fichier": "resources/views/version.php",
      "langage": "php",
      "lignes": 3,
      "taille_bytes": 171,
      "entrees": [],
      "sorties": [],
      "appelle": [],
      "est_appele_par": [],
      "type_noeud": "standard"
    },
    "resources/views/usage.php": {
      "fichier": "resources/views/usage.php",
      "langage": "php",
      "lignes": 4,
      "taille_bytes": 197,
      "entrees": [],
      "sorties": [],
      "appelle": [],
      "est_appele_par": [],
      "type_noeud": "standard"
    },
    "resources/views/installers/plugin-browser.php": {
      "fichier": "resources/views/installers/plugin-browser.php",
      "langage": "php",
      "lignes": 22,
      "taille_bytes": 630,
      "entrees": [],
      "sorties": [],
      "appelle": [],
      "est_appele_par": [],
      "type_noeud": "standard"
    },
    "resources/views/components/two-column-detail.php": {
      "fichier": "resources/views/components/two-column-detail.php",
      "langage": "php",
      "lignes": 12,
      "taille_bytes": 332,
      "entrees": [],
      "sorties": [],
      "appelle": [],
      "est_appele_par": [],
      "type_noeud": "standard"
    },
    "resources/views/components/new-line.php": {
      "fichier": "resources/views/components/new-line.php",
      "langage": "php",
      "lignes": 1,
      "taille_bytes": 12,
      "entrees": [],
      "sorties": [],
      "appelle": [],
      "est_appele_par": [],
      "type_noeud": "standard"
    },
    "resources/views/components/badge.php": {
      "fichier": "resources/views/components/badge.php",
      "langage": "php",
      "lignes": 17,
      "taille_bytes": 413,
      "entrees": [],
      "sorties": [],
      "appelle": [],
      "est_appele_par": [],
      "type_noeud": "standard"
    },
    "src/Plugin.php": {
      "fichier": "src/Plugin.php",
      "langage": "php",
      "lignes": 29,
      "taille_bytes": 599,
      "entrees": [],
      "sorties": [],
      "appelle": [],
      "est_appele_par": [],
      "type_noeud": "standard"
    },
    "src/Functions.php": {
      "fichier": "src/Functions.php",
      "langage": "php",
      "lignes": 332,
      "taille_bytes": 10309,
      "entrees": [
        "PHPUnit\\Framework\\TestCase",
        "Pest\\Browser\\Api\\ArrayablePendingAwaitablePage",
        "Pest\\Browser\\Api\\PendingAwaitablePage",
        "Pest\\Concerns\\Expectable",
        "Pest\\Configuration",
        "Pest\\Exceptions\\AfterAllWithinDescribe",
        "Pest\\Exceptions\\BeforeAllWithinDescribe",
        "Pest\\Expectation",
        "Pest\\Installers\\PluginBrowser",
        "Pest\\Mutate\\Contracts\\MutationTestRunner",
        "Pest\\Mutate\\Repositories\\ConfigurationRepository",
        "Pest\\PendingCalls\\AfterEachCall",
        "Pest\\PendingCalls\\BeforeEachCall",
        "Pest\\PendingCalls\\DescribeCall",
        "Pest\\PendingCalls\\TestCall",
        "Pest\\PendingCalls\\UsesCall",
        "Pest\\Repositories\\DatasetsRepository",
        "Pest\\Support\\Backtrace",
        "Pest\\Support\\Container",
        "Pest\\Support\\DatasetInfo",
        "Pest\\Support\\Description",
        "Pest\\Support\\HigherOrderTapProxy",
        "Pest\\TestSuite"
      ],
      "sorties": [
        "function afterAll",
        "function afterEach",
        "function beforeAll",
        "function beforeEach",
        "function covers",
        "function dataset",
        "function describe",
        "function expect",
        "function fixture",
        "function it",
        "function mutates",
        "function pest",
        "function test",
        "function todo",
        "function uses",
        "function visit"
      ],
      "appelle": [],
      "est_appele_par": [],
      "type_noeud": "standard"
    },
    "src/Preset.php": {
      "fichier": "src/Preset.php",
      "langage": "php",
      "lignes": 156,
      "taille_bytes": 3943,
      "entrees": [
        "Closure",
        "Pest\\ArchPresets\\AbstractPreset",
        "Pest\\ArchPresets\\Custom",
        "Pest\\ArchPresets\\Laravel",
        "Pest\\ArchPresets\\Php",
        "Pest\\ArchPresets\\Relaxed",
        "Pest\\ArchPresets\\Security",
        "Pest\\ArchPresets\\Strict",
        "Pest\\Arch\\Support\\Composer",
        "Pest\\Exceptions\\InvalidArgumentException",
        "Pest\\PendingCalls\\TestCall",
        "stdClass"
      ],
      "sorties": [
        "public func tion"
      ],
      "appelle": [
        "src/Support/Closure.php"
      ],
      "est_appele_par": [],
      "type_noeud": "standard"
    },
    "src/Expectation.php": {
      "fichier": "src/Expectation.php",
      "langage": "php",
      "lignes": 1128,
      "taille_bytes": 35628,
      "entrees": [
        "Attribute",
        "BadMethodCallException",
        "Closure",
        "Extendable",
        "InvalidArgumentException",
        "OutOfRangeException",
        "PHPUnit\\Architecture\\Elements\\ObjectDescription",
        "PHPUnit\\Framework\\ExpectationFailedException",
        "Pest\\Arch\\Contracts\\ArchExpectation",
        "Pest\\Arch\\Expectations\\Targeted",
        "Pest\\Arch\\Expectations\\ToBeUsedIn",
        "Pest\\Arch\\Expectations\\ToBeUsedInNothing",
        "Pest\\Arch\\Expectations\\ToOnlyBeUsedIn",
        "Pest\\Arch\\Expectations\\ToOnlyUse",
        "Pest\\Arch\\Expectations\\ToUse",
        "Pest\\Arch\\Expectations\\ToUseNothing",
        "Pest\\Arch\\PendingArchExpectation",
        "Pest\\Arch\\Support\\FileLineFinder",
        "Pest\\Concerns\\Extendable",
        "Pest\\Concerns\\Pipeable",
        "Pest\\Concerns\\Retrievable",
        "Pest\\Exceptions\\ExpectationNotFound",
        "Pest\\Exceptions\\InvalidExpectation",
        "Pest\\Exceptions\\InvalidExpectationValue",
        "Pest\\Expectations\\EachExpectation",
        "Pest\\Expectations\\HigherOrderExpectation",
        "Pest\\Expectations\\OppositeExpectation",
        "Pest\\Matchers\\Any",
        "Pest\\Support\\ExpectationPipeline",
        "Pest\\Support\\Reflection",
        "Pipeable",
        "ReflectionEnum",
        "ReflectionMethod",
        "ReflectionProperty",
        "Retrievable"
      ],
      "sorties": [
        "public func tion"
      ],
      "appelle": [
        "src/Factories/Attribute.php",
        "src/Support/Closure.php"
      ],
      "est_appele_par": [],
      "type_noeud": "point_entree"
    },
    "src/Panic.php": {
      "fichier": "src/Panic.php",
      "langage": "php",
      "lignes": 70,
      "taille_bytes": 1562,
      "entrees": [
        "NunoMaduro\\Collision\\Writer",
        "Pest\\Exceptions\\TestDescriptionMissing",
        "Pest\\Support\\Container",
        "Symfony\\Component\\Console\\Output\\ConsoleOutput",
        "Symfony\\Component\\Console\\Output\\OutputInterface",
        "Throwable",
        "Whoops\\Exception\\Inspector"
      ],
      "sorties": [],
      "appelle": [],
      "est_appele_par": [],
      "type_noeud": "standard"
    },
    "src/Kernel.php": {
      "fichier": "src/Kernel.php",
      "langage": "php",
      "lignes": 171,
      "taille_bytes": 4624,
      "entrees": [
        "NunoMaduro\\Collision\\Writer",
        "PHPUnit\\TestRunner\\TestResult\\Facade",
        "PHPUnit\\TextUI\\Application",
        "PHPUnit\\TextUI\\Configuration\\Registry",
        "Pest\\Contracts\\Bootstrapper",
        "Pest\\Exceptions\\FatalException",
        "Pest\\Exceptions\\NoDirtyTestsFound",
        "Pest\\Plugins\\Actions\\CallsAddsOutput",
        "Pest\\Plugins\\Actions\\CallsBoot",
        "Pest\\Plugins\\Actions\\CallsHandleArguments",
        "Pest\\Plugins\\Actions\\CallsHandleOriginalArguments",
        "Pest\\Plugins\\Actions\\CallsTerminable",
        "Pest\\Support\\Container",
        "Pest\\Support\\Reflection",
        "Pest\\Support\\View",
        "Symfony\\Component\\Console\\Input\\InputInterface",
        "Symfony\\Component\\Console\\Output\\OutputInterface",
        "Throwable",
        "Whoops\\Exception\\Inspector"
      ],
      "sorties": [
        "public func tion"
      ],
      "appelle": [],
      "est_appele_par": [],
      "type_noeud": "standard"
    },
    "src/KernelDump.php": {
      "fichier": "src/KernelDump.php",
      "langage": "php",
      "lignes": 113,
      "taille_bytes": 2529,
      "entrees": [
        "Pest\\Support\\View",
        "Symfony\\Component\\Console\\Output\\OutputInterface"
      ],
      "sorties": [
        "public func tion"
      ],
      "appelle": [],
      "est_appele_par": [],
      "type_noeud": "standard"
    },
    "src/Pest.php": {
      "fichier": "src/Pest.php",
      "langage": "php",
      "lignes": 15,
      "taille_bytes": 229,
      "entrees": [],
      "sorties": [
        "function testDirectory",
        "function version"
      ],
      "appelle": [],
      "est_appele_par": [],
      "type_noeud": "standard"
    },
    "src/Result.php": {
      "fichier": "src/Result.php",
      "langage": "php",
      "lignes": 43,
      "taille_bytes": 990,
      "entrees": [
        "PHPUnit\\TestRunner\\TestResult\\TestResult",
        "PHPUnit\\TextUI\\Configuration\\Configuration",
        "PHPUnit\\TextUI\\ShellExitCodeCalculator"
      ],
      "sorties": [],
      "appelle": [],
      "est_appele_par": [],
      "type_noeud": "standard"
    },
    "src/Configuration.php": {
      "fichier": "src/Configuration.php",
      "langage": "php",
      "lignes": 131,
      "taille_bytes": 3178,
      "entrees": [
        "Pest\\PendingCalls\\BeforeEachCall",
        "Pest\\PendingCalls\\UsesCall"
      ],
      "sorties": [
        "public func tion"
      ],
      "appelle": [],
      "est_appele_par": [],
      "type_noeud": "standard"
    },
    "src/TestSuite.php": {
      "fichier": "src/TestSuite.php",
      "langage": "php",
      "lignes": 134,
      "taille_bytes": 3470,
      "entrees": [
        "PHPUnit\\Framework\\TestCase",
        "Pest\\Exceptions\\InvalidPestCommand",
        "Pest\\Repositories\\AfterAllRepository",
        "Pest\\Repositories\\AfterEachRepository",
        "Pest\\Repositories\\BeforeAllRepository",
        "Pest\\Repositories\\BeforeEachRepository",
        "Pest\\Repositories\\SnapshotRepository",
        "Pest\\Repositories\\TestRepository",
        "Pest\\Support\\Str"
      ],
      "sorties": [
        "public func tion"
      ],
      "appelle": [],
      "est_appele_par": [],
      "type_noeud": "standard"
    },
    "src/Logging/Converter.php": {
      "fichier": "src/Logging/Converter.php",
      "langage": "php",
      "lignes": 275,
      "taille_bytes": 7793,
      "entrees": [
        "NunoMaduro\\Collision\\Adapters\\Phpunit\\State",
        "PHPUnit\\Event\\Code\\Test",
        "PHPUnit\\Event\\Code\\TestMethod",
        "PHPUnit\\Event\\Code\\Throwable",
        "PHPUnit\\Event\\TestSuite\\TestSuite",
        "PHPUnit\\Event\\TestSuite\\TestSuiteForTestMethodWithDataProvider",
        "PHPUnit\\Event\\Test\\AfterLastTestMethodErrored",
        "PHPUnit\\Event\\Test\\BeforeFirstTestMethodErrored",
        "PHPUnit\\Event\\Test\\ConsideredRisky",
        "PHPUnit\\Event\\Test\\Errored",
        "PHPUnit\\Event\\Test\\Failed",
        "PHPUnit\\Event\\Test\\MarkedIncomplete",
        "PHPUnit\\Event\\Test\\Skipped",
        "PHPUnit\\Framework\\Exception",
        "PHPUnit\\TestRunner\\TestResult\\TestResult",
        "Pest\\Exceptions\\ShouldNotHappen",
        "Pest\\Support\\StateGenerator",
        "Pest\\Support\\Str"
      ],
      "sorties": [
        "public func tion"
      ],
      "appelle": [],
      "est_appele_par": [],
      "type_noeud": "standard"
    },
    "src/Logging/TeamCity/ServiceMessage.php": {
      "fichier": "src/Logging/TeamCity/ServiceMessage.php",
      "langage": "php",
      "lignes": 145,
      "taille_bytes": 3648,
      "entrees": [],
      "sorties": [
        "public func tion"
      ],
      "appelle": [],
      "est_appele_par": [],
      "type_noeud": "standard"
    },
    "src/Logging/TeamCity/TeamCityLogger.php": {
      "fichier": "src/Logging/TeamCity/TeamCityLogger.php",
      "langage": "php",
      "lignes": 294,
      "taille_bytes": 9357,
      "entrees": [
        "NunoMaduro\\Collision\\Adapters\\Phpunit\\Style",
        "PHPUnit\\Event\\Code\\Test",
        "PHPUnit\\Event\\EventFacadeIsSealedException",
        "PHPUnit\\Event\\Facade",
        "PHPUnit\\Event\\Telemetry\\Duration",
        "PHPUnit\\Event\\Telemetry\\HRTime",
        "PHPUnit\\Event\\Telemetry\\Info",
        "PHPUnit\\Event\\Telemetry\\Snapshot",
        "PHPUnit\\Event\\TestRunner\\ExecutionFinished",
        "PHPUnit\\Event\\TestSuite\\Finished",
        "PHPUnit\\Event\\TestSuite\\Started",
        "PHPUnit\\Event\\Test\\ConsideredRisky",
        "PHPUnit\\Event\\Test\\Errored",
        "PHPUnit\\Event\\Test\\Failed",
        "PHPUnit\\Event\\Test\\Finished",
        "PHPUnit\\Event\\Test\\Prepared",
        "PHPUnit\\Event\\Test\\Skipped",
        "PHPUnit\\Event\\UnknownSubscriberTypeException",
        "PHPUnit\\TestRunner\\TestResult\\Facade",
        "Pest\\Exceptions\\ShouldNotHappen",
        "Pest\\Logging\\Converter",
        "Pest\\Logging\\TeamCity\\Subscriber\\TestConsideredRiskySubscriber",
        "Pest\\Logging\\TeamCity\\Subscriber\\TestErroredSubscriber",
        "Pest\\Logging\\TeamCity\\Subscriber\\TestExecutionFinishedSubscriber",
        "Pest\\Logging\\TeamCity\\Subscriber\\TestFailedSubscriber",
        "Pest\\Logging\\TeamCity\\Subscriber\\TestFinishedSubscriber",
        "Pest\\Logging\\TeamCity\\Subscriber\\TestPreparedSubscriber",
        "Pest\\Logging\\TeamCity\\Subscriber\\TestSkippedSubscriber",
        "Pest\\Logging\\TeamCity\\Subscriber\\TestSuiteFinishedSubscriber",
        "Pest\\Logging\\TeamCity\\Subscriber\\TestSuiteStartedSubscriber",
        "ReflectionClass",
        "Symfony\\Component\\Console\\Output\\ConsoleOutput",
        "Symfony\\Component\\Console\\Output\\OutputInterface"
      ],
      "sorties": [
        "public func tion"
      ],
      "appelle": [],
      "est_appele_par": [],
      "type_noeud": "standard"
    },
    "src/Logging/TeamCity/Subscriber/TestFailedSubscriber.php": {
      "fichier": "src/Logging/TeamCity/Subscriber/TestFailedSubscriber.php",
      "langage": "php",
      "lignes": 19,
      "taille_bytes": 361,
      "entrees": [
        "PHPUnit\\Event\\Test\\Failed",
        "PHPUnit\\Event\\Test\\FailedSubscriber"
      ],
      "sorties": [
        "public func tion"
      ],
      "appelle": [],
      "est_appele_par": [],
      "type_noeud": "standard"
    },
    "src/Logging/TeamCity/Subscriber/TestExecutionFinishedSubscriber.php": {
      "fichier": "src/Logging/TeamCity/Subscriber/TestExecutionFinishedSubscriber.php",
      "langage": "php",
      "lignes": 19,
      "taille_bytes": 439,
      "entrees": [
        "PHPUnit\\Event\\TestRunner\\ExecutionFinished",
        "PHPUnit\\Event\\TestRunner\\ExecutionFinishedSubscriber"
      ],
      "sorties": [
        "public func tion"
      ],
      "appelle": [],
      "est_appele_par": [],
      "type_noeud": "standard"
    },
    "src/Logging/TeamCity/Subscriber/TestFinishedSubscriber.php": {
      "fichier": "src/Logging/TeamCity/Subscriber/TestFinishedSubscriber.php",
      "langage": "php",
      "lignes": 19,
      "taille_bytes": 373,
      "entrees": [
        "PHPUnit\\Event\\Test\\Finished",
        "PHPUnit\\Event\\Test\\FinishedSubscriber"
      ],
      "sorties": [
        "public func tion"
      ],
      "appelle": [],
      "est_appele_par": [],
      "type_noeud": "standard"
    },
    "src/Logging/TeamCity/Subscriber/TestSkippedSubscriber.php": {
      "fichier": "src/Logging/TeamCity/Subscriber/TestSkippedSubscriber.php",
      "langage": "php",
      "lignes": 19,
      "taille_bytes": 367,
      "entrees": [
        "PHPUnit\\Event\\Test\\Skipped",
        "PHPUnit\\Event\\Test\\SkippedSubscriber"
      ],
      "sorties": [
        "public func tion"
      ],
      "appelle": [],
      "est_appele_par": [],
      "type_noeud": "standard"
    },
    "src/Logging/TeamCity/Subscriber/TestSuiteFinishedSubscriber.php": {
      "fichier": "src/Logging/TeamCity/Subscriber/TestSuiteFinishedSubscriber.php",
      "langage": "php",
      "lignes": 19,
      "taille_bytes": 393,
      "entrees": [
        "PHPUnit\\Event\\TestSuite\\Finished",
        "PHPUnit\\Event\\TestSuite\\FinishedSubscriber"
      ],
      "sorties": [
        "public func tion"
      ],
      "appelle": [],
      "est_appele_par": [],
      "type_noeud": "standard"
    },
    "src/Logging/TeamCity/Subscriber/TestSuiteStartedSubscriber.php": {
      "fichier": "src/Logging/TeamCity/Subscriber/TestSuiteStartedSubscriber.php",
      "langage": "php",
      "lignes": 19,
      "taille_bytes": 387,
      "entrees": [
        "PHPUnit\\Event\\TestSuite\\Started",
        "PHPUnit\\Event\\TestSuite\\StartedSubscriber"
      ],
      "sorties": [
        "public func tion"
      ],
      "appelle": [],
      "est_appele_par": [],
      "type_noeud": "standard"
    },
    "src/Logging/TeamCity/Subscriber/Subscriber.php": {
      "fichier": "src/Logging/TeamCity/Subscriber/Subscriber.php",
      "langage": "php",
      "lignes": 26,
      "taille_bytes": 517,
      "entrees": [
        "Pest\\Logging\\TeamCity\\TeamCityLogger"
      ],
      "sorties": [
        "abstract class Subscriber",
        "public func tion"
      ],
      "appelle": [],
      "est_appele_par": [],
      "type_noeud": "standard"
    },
    "src/Logging/TeamCity/Subscriber/TestErroredSubscriber.php": {
      "fichier": "src/Logging/TeamCity/Subscriber/TestErroredSubscriber.php",
      "langage": "php",
      "lignes": 19,
      "taille_bytes": 367,
      "entrees": [
        "PHPUnit\\Event\\Test\\Errored",
        "PHPUnit\\Event\\Test\\ErroredSubscriber"
      ],
      "sorties": [
        "public func tion"
      ],
      "appelle": [],
      "est_appele_par": [],
      "type_noeud": "standard"
    },
    "src/Logging/TeamCity/Subscriber/TestConsideredRiskySubscriber.php": {
      "fichier": "src/Logging/TeamCity/Subscriber/TestConsideredRiskySubscriber.php",
      "langage": "php",
      "lignes": 19,
      "taille_bytes": 415,
      "entrees": [
        "PHPUnit\\Event\\Test\\ConsideredRisky",
        "PHPUnit\\Event\\Test\\ConsideredRiskySubscriber"
      ],
      "sorties": [
        "public func tion"
      ],
      "appelle": [],
      "est_appele_par": [],
      "type_noeud": "standard"
    },
    "src/Logging/TeamCity/Subscriber/TestPreparedSubscriber.php": {
      "fichier": "src/Logging/TeamCity/Subscriber/TestPreparedSubscriber.php",
      "langage": "php",
      "lignes": 19,
      "taille_bytes": 373,
      "entrees": [
        "PHPUnit\\Event\\Test\\Prepared",
        "PHPUnit\\Event\\Test\\PreparedSubscriber"
      ],
      "sorties": [
        "public func tion"
      ],
      "appelle": [],
      "est_appele_par": [],
      "type_noeud": "standard"
    },
    "src/Expectations/HigherOrderExpectation.php": {
      "fichier": "src/Expectations/HigherOrderExpectation.php",
      "langage": "php",
      "lignes": 189,
      "taille_bytes": 4773,
      "entrees": [
        "Closure",
        "Pest\\Concerns\\Retrievable",
        "Pest\\Expectation",
        "Retrievable"
      ],
      "sorties": [
        "public func tion"
      ],
      "appelle": [
        "src/Support/Closure.php"
      ],
      "est_appele_par": [],
      "type_noeud": "standard"
    },
    "src/Expectations/EachExpectation.php": {
      "fichier": "src/Expectations/EachExpectation.php",
      "langage": "php",
      "lignes": 85,
      "taille_bytes": 1816,
      "entrees": [
        "Pest\\Expectation",
        "function"
      ],
      "sorties": [
        "public func tion"
      ],
      "appelle": [],
      "est_appele_par": [],
      "type_noeud": "standard"
    },
    "src/Expectations/OppositeExpectation.php": {
      "fichier": "src/Expectations/OppositeExpectation.php",
      "langage": "php",
      "lignes": 893,
      "taille_bytes": 31670,
      "entrees": [
        "Attribute",
        "PHPUnit\\Architecture\\Elements\\ObjectDescription",
        "PHPUnit\\Framework\\AssertionFailedError",
        "PHPUnit\\Framework\\ExpectationFailedException",
        "Pest\\Arch\\Contracts\\ArchExpectation",
        "Pest\\Arch\\Expectations\\Targeted",
        "Pest\\Arch\\Expectations\\ToBeUsedIn",
        "Pest\\Arch\\Expectations\\ToBeUsedInNothing",
        "Pest\\Arch\\Expectations\\ToUse",
        "Pest\\Arch\\GroupArchExpectation",
        "Pest\\Arch\\PendingArchExpectation",
        "Pest\\Arch\\SingleArchExpectation",
        "Pest\\Arch\\Support\\FileLineFinder",
        "Pest\\Exceptions\\InvalidExpectation",
        "Pest\\Exceptions\\MissingDependency",
        "Pest\\Expectation",
        "Pest\\Support\\Arr",
        "Pest\\Support\\Exporter",
        "Pest\\Support\\Reflection",
        "ReflectionMethod",
        "ReflectionProperty",
        "Spoofchecker",
        "stdClass"
      ],
      "sorties": [
        "public func tion"
      ],
      "appelle": [
        "src/Factories/Attribute.php"
      ],
      "est_appele_par": [],
      "type_noeud": "standard"
    },
    "src/TestCaseMethodFilters/AssigneeTestCaseFilter.php": {
      "fichier": "src/TestCaseMethodFilters/AssigneeTestCaseFilter.php",
      "langage": "php",
      "lignes": 27,
      "taille_bytes": 634,
      "entrees": [
        "Pest\\Contracts\\TestCaseMethodFilter",
        "Pest\\Factories\\TestCaseMethodFactory"
      ],
      "sorties": [
        "public func tion"
      ],
      "appelle": [],
      "est_appele_par": [],
      "type_noeud": "standard"
    },
    "src/TestCaseMethodFilters/PrTestCaseFilter.php": {
      "fichier": "src/TestCaseMethodFilters/PrTestCaseFilter.php",
      "langage": "php",
      "lignes": 27,
      "taille_bytes": 551,
      "entrees": [
        "Pest\\Contracts\\TestCaseMethodFilter",
        "Pest\\Factories\\TestCaseMethodFactory"
      ],
      "sorties": [
        "public func tion"
      ],
      "appelle": [],
      "est_appele_par": [],
      "type_noeud": "standard"
    },
    "src/TestCaseMethodFilters/IssueTestCaseFilter.php": {
      "fichier": "src/TestCaseMethodFilters/IssueTestCaseFilter.php",
      "langage": "php",
      "lignes": 27,
      "taille_bytes": 557,
      "entrees": [
        "Pest\\Contracts\\TestCaseMethodFilter",
        "Pest\\Factories\\TestCaseMethodFactory"
      ],
      "sorties": [
        "public func tion"
      ],
      "appelle": [],
      "est_appele_par": [],
      "type_noeud": "standard"
    },
    "src/TestCaseMethodFilters/NotesTestCaseFilter.php": {
      "fichier": "src/TestCaseMethodFilters/NotesTestCaseFilter.php",
      "langage": "php",
      "lignes": 19,
      "taille_bytes": 402,
      "entrees": [
        "Pest\\Contracts\\TestCaseMethodFilter",
        "Pest\\Factories\\TestCaseMethodFactory"
      ],
      "sorties": [
        "public func tion"
      ],
      "appelle": [],
      "est_appele_par": [],
      "type_noeud": "standard"
    },
    "src/TestCaseMethodFilters/TodoTestCaseFilter.php": {
      "fichier": "src/TestCaseMethodFilters/TodoTestCaseFilter.php",
      "langage": "php",
      "lignes": 19,
      "taille_bytes": 393,
      "entrees": [
        "Pest\\Contracts\\TestCaseMethodFilter",
        "Pest\\Factories\\TestCaseMethodFactory"
      ],
      "sorties": [
        "public func tion"
      ],
      "appelle": [],
      "est_appele_par": [],
      "type_noeud": "standard"
    },
    "src/ArchPresets/Php.php": {
      "fichier": "src/ArchPresets/Php.php",
      "langage": "php",
      "lignes": 93,
      "taille_bytes": 2717,
      "entrees": [],
      "sorties": [
        "public func tion"
      ],
      "appelle": [],
      "est_appele_par": [],
      "type_noeud": "standard"
    },
    "src/ArchPresets/Relaxed.php": {
      "fichier": "src/ArchPresets/Relaxed.php",
      "langage": "php",
      "lignes": 26,
      "taille_bytes": 646,
      "entrees": [
        "Pest\\Arch\\Contracts\\ArchExpectation",
        "Pest\\Expectation"
      ],
      "sorties": [
        "public func tion"
      ],
      "appelle": [],
      "est_appele_par": [],
      "type_noeud": "standard"
    },
    "src/ArchPresets/AbstractPreset.php": {
      "fichier": "src/ArchPresets/AbstractPreset.php",
      "langage": "php",
      "lignes": 74,
      "taille_bytes": 1784,
      "entrees": [
        "Pest\\Arch\\Contracts\\ArchExpectation",
        "Pest\\Expectation"
      ],
      "sorties": [
        "abstract class AbstractPreset",
        "public func tion"
      ],
      "appelle": [],
      "est_appele_par": [],
      "type_noeud": "standard"
    },
    "src/ArchPresets/Laravel.php": {
      "fichier": "src/ArchPresets/Laravel.php",
      "langage": "php",
      "lignes": 177,
      "taille_bytes": 5680,
      "entrees": [
        "Throwable"
      ],
      "sorties": [
        "public func tion"
      ],
      "appelle": [],
      "est_appele_par": [],
      "type_noeud": "standard"
    },
    "src/ArchPresets/Custom.php": {
      "fichier": "src/ArchPresets/Custom.php",
      "langage": "php",
      "lignes": 45,
      "taille_bytes": 937,
      "entrees": [
        "Closure",
        "Pest\\Arch\\Contracts\\ArchExpectation",
        "Pest\\Expectation"
      ],
      "sorties": [
        "public func tion"
      ],
      "appelle": [
        "src/Support/Closure.php"
      ],
      "est_appele_par": [],
      "type_noeud": "standard"
    },
    "src/ArchPresets/Strict.php": {
      "fichier": "src/ArchPresets/Strict.php",
      "langage": "php",
      "lignes": 33,
      "taille_bytes": 950,
      "entrees": [
        "Pest\\Arch\\Contracts\\ArchExpectation",
        "Pest\\Expectation"
      ],
      "sorties": [
        "public func tion"
      ],
      "appelle": [],
      "est_appele_par": [],
      "type_noeud": "standard"
    },
    "src/ArchPresets/Security.php": {
      "fichier": "src/ArchPresets/Security.php",
      "langage": "php",
      "lignes": 40,
      "taille_bytes": 762,
      "entrees": [],
      "sorties": [
        "public func tion"
      ],
      "appelle": [],
      "est_appele_par": [],
      "type_noeud": "standard"
    },
    "src/Factories/TestCaseFactory.php": {
      "fichier": "src/Factories/TestCaseFactory.php",
      "langage": "php",
      "lignes": 250,
      "taille_bytes": 7332,
      "entrees": [
        "HigherOrderable",
        "PHPUnit\\Framework\\TestCase",
        "ParseError",
        "Pest\\Concerns",
        "Pest\\Contracts\\HasPrintableTestCaseName",
        "Pest\\Evaluators\\Attributes",
        "Pest\\Exceptions\\DatasetMissing",
        "Pest\\Exceptions\\ShouldNotHappen",
        "Pest\\Exceptions\\TestAlreadyExist",
        "Pest\\Exceptions\\TestClosureMustNotBeStatic",
        "Pest\\Exceptions\\TestDescriptionMissing",
        "Pest\\Factories\\Concerns\\HigherOrderable",
        "Pest\\Repositories\\DatasetsRepository",
        "Pest\\Support\\Reflection",
        "Pest\\Support\\Str",
        "Pest\\TestSuite",
        "RuntimeException"
      ],
      "sorties": [
        "public func tion"
      ],
      "appelle": [
        "src/Factories/Concerns/HigherOrderable.php"
      ],
      "est_appele_par": [],
      "type_noeud": "standard"
    },
    "src/Factories/TestCaseMethodFactory.php": {
      "fichier": "src/Factories/TestCaseMethodFactory.php",
      "langage": "php",
      "lignes": 260,
      "taille_bytes": 6619,
      "entrees": [
        "Closure",
        "HigherOrderable",
        "PHPUnit\\Framework\\Assert",
        "PHPUnit\\Framework\\Attributes\\DataProvider",
        "PHPUnit\\Framework\\TestCase",
        "Pest\\Evaluators\\Attributes",
        "Pest\\Exceptions\\ShouldNotHappen",
        "Pest\\Factories\\Concerns\\HigherOrderable",
        "Pest\\Repositories\\DatasetsRepository",
        "Pest\\Support\\Str",
        "Pest\\TestSuite"
      ],
      "sorties": [
        "public func tion"
      ],
      "appelle": [
        "src/Factories/Concerns/HigherOrderable.php",
        "src/Support/Closure.php"
      ],
      "est_appele_par": [],
      "type_noeud": "point_entree"
    },
    "src/Factories/Attribute.php": {
      "fichier": "src/Factories/Attribute.php",
      "langage": "php",
      "lignes": 19,
      "taille_bytes": 276,
      "entrees": [],
      "sorties": [
        "public func tion"
      ],
      "appelle": [],
      "est_appele_par": [
        "src/Expectation.php",
        "src/Expectations/OppositeExpectation.php"
      ],
      "type_noeud": "standard"
    },
    "src/Factories/Covers/CoversClass.php": {
      "fichier": "src/Factories/Covers/CoversClass.php",
      "langage": "php",
      "lignes": 13,
      "taille_bytes": 173,
      "entrees": [],
      "sorties": [
        "public func tion"
      ],
      "appelle": [],
      "est_appele_par": [],
      "type_noeud": "standard"
    },
    "src/Factories/Covers/CoversFunction.php": {
      "fichier": "src/Factories/Covers/CoversFunction.php",
      "langage": "php",
      "lignes": 13,
      "taille_bytes": 179,
      "entrees": [],
      "sorties": [
        "public func tion"
      ],
      "appelle": [],
      "est_appele_par": [],
      "type_noeud": "standard"
    },
    "src/Factories/Concerns/HigherOrderable.php": {
      "fichier": "src/Factories/Concerns/HigherOrderable.php",
      "langage": "php",
      "lignes": 35,
      "taille_bytes": 820,
      "entrees": [
        "Pest\\Support\\HigherOrderMessageCollection"
      ],
      "sorties": [
        "trait HigherOrderable"
      ],
      "appelle": [],
      "est_appele_par": [
        "src/Factories/TestCaseFactory.php",
        "src/Factories/TestCaseMethodFactory.php"
      ],
      "type_noeud": "standard"
    },
    "src/Bootstrappers/BootFiles.php": {
      "fichier": "src/Bootstrappers/BootFiles.php",
      "langage": "php",
      "lignes": 96,
      "taille_bytes": 2481,
      "entrees": [
        "$filename",
        "Pest\\Contracts\\Bootstrapper",
        "Pest\\Exceptions\\FatalException",
        "Pest\\Support\\DatasetInfo",
        "Pest\\Support\\Str",
        "Pest\\TestSuite",
        "RecursiveDirectoryIterator",
        "RecursiveIteratorIterator",
        "SebastianBergmann\\FileIterator\\Facade",
        "function"
      ],
      "sorties": [
        "public func tion"
      ],
      "appelle": [],
      "est_appele_par": [],
      "type_noeud": "standard"
    },
    "src/Bootstrappers/BootExcludeList.php": {
      "fichier": "src/Bootstrappers/BootExcludeList.php",
      "langage": "php",
      "lignes": 39,
      "taille_bytes": 765,
      "entrees": [
        "PHPUnit\\Util\\ExcludeList",
        "Pest\\Contracts\\Bootstrapper"
      ],
      "sorties": [
        "public func tion"
      ],
      "appelle": [],
      "est_appele_par": [],
      "type_noeud": "standard"
    },
    "src/Bootstrappers/BootOverrides.php": {
      "fichier": "src/Bootstrappers/BootOverrides.php",
      "langage": "php",
      "lignes": 46,
      "taille_bytes": 1176,
      "entrees": [
        "$file",
        "Pest\\Contracts\\Bootstrapper",
        "Pest\\Exceptions\\ShouldNotHappen"
      ],
      "sorties": [
        "public func tion"
      ],
      "appelle": [],
      "est_appele_par": [],
      "type_noeud": "standard"
    },
    "src/Bootstrappers/BootKernelDump.php": {
      "fichier": "src/Bootstrappers/BootKernelDump.php",
      "langage": "php",
      "lignes": 37,
      "taille_bytes": 703,
      "entrees": [
        "Pest\\Contracts\\Bootstrapper",
        "Pest\\KernelDump",
        "Pest\\Support\\Container",
        "Symfony\\Component\\Console\\Output\\OutputInterface"
      ],
      "sorties": [
        "public func tion"
      ],
      "appelle": [],
      "est_appele_par": [],
      "type_noeud": "standard"
    },
    "src/Bootstrappers/BootView.php": {
      "fichier": "src/Bootstrappers/BootView.php",
      "langage": "php",
      "lignes": 32,
      "taille_bytes": 555,
      "entrees": [
        "Pest\\Contracts\\Bootstrapper",
        "Pest\\Support\\View",
        "Symfony\\Component\\Console\\Output\\OutputInterface"
      ],
      "sorties": [
        "public func tion"
      ],
      "appelle": [],
      "est_appele_par": [],
      "type_noeud": "standard"
    },
    "src/Bootstrappers/BootSubscribers.php": {
      "fichier": "src/Bootstrappers/BootSubscribers.php",
      "langage": "php",
      "lignes": 50,
      "taille_bytes": 1159,
      "entrees": [
        "PHPUnit\\Event",
        "PHPUnit\\Event\\Subscriber",
        "Pest\\Contracts\\Bootstrapper",
        "Pest\\Subscribers",
        "Pest\\Support\\Container"
      ],
      "sorties": [
        "public func tion"
      ],
      "appelle": [],
      "est_appele_par": [],
      "type_noeud": "standard"
    },
    "src/TestCaseFilters/GitDirtyTestCaseFilter.php": {
      "fichier": "src/TestCaseFilters/GitDirtyTestCaseFilter.php",
      "langage": "php",
      "lignes": 93,
      "taille_bytes": 2589,
      "entrees": [
        "Pest\\Contracts\\TestCaseFilter",
        "Pest\\Exceptions\\MissingDependency",
        "Pest\\Exceptions\\NoDirtyTestsFound",
        "Pest\\Panic",
        "Pest\\TestSuite",
        "Symfony\\Component\\Process\\Process"
      ],
      "sorties": [
        "public func tion"
      ],
      "appelle": [],
      "est_appele_par": [],
      "type_noeud": "standard"
    },
    "src/PendingCalls/TestCall.php": {
      "fichier": "src/PendingCalls/TestCall.php",
      "langage": "php",
      "lignes": 770,
      "taille_bytes": 21940,
      "entrees": [
        "Closure",
        "Describable",
        "PHPUnit\\Framework\\AssertionFailedError",
        "PHPUnit\\Framework\\TestCase",
        "Pest\\Concerns\\Testable",
        "Pest\\Exceptions\\InvalidArgumentException",
        "Pest\\Exceptions\\TestDescriptionMissing",
        "Pest\\Factories\\Attribute",
        "Pest\\Factories\\TestCaseMethodFactory",
        "Pest\\Mutate\\Repositories\\ConfigurationRepository",
        "Pest\\PendingCalls\\Concerns\\Describable",
        "Pest\\Plugins\\Environment",
        "Pest\\Plugins\\Only",
        "Pest\\Support\\Backtrace",
        "Pest\\Support\\Container",
        "Pest\\Support\\Exporter",
        "Pest\\Support\\HigherOrderCallables",
        "Pest\\Support\\NullClosure",
        "Pest\\Support\\Str",
        "Pest\\TestSuite"
      ],
      "sorties": [
        "public func tion"
      ],
      "appelle": [
        "src/PendingCalls/Concerns/Describable.php",
        "src/Support/Closure.php"
      ],
      "est_appele_par": [],
      "type_noeud": "point_entree"
    },
    "src/PendingCalls/BeforeEachCall.php": {
      "fichier": "src/PendingCalls/BeforeEachCall.php",
      "langage": "php",
      "lignes": 126,
      "taille_bytes": 3298,
      "entrees": [
        "Closure",
        "Describable",
        "Pest\\Exceptions\\AfterBeforeTestFunction",
        "Pest\\PendingCalls\\Concerns\\Describable",
        "Pest\\Support\\Arr",
        "Pest\\Support\\Backtrace",
        "Pest\\Support\\ChainableClosure",
        "Pest\\Support\\HigherOrderMessageCollection",
        "Pest\\Support\\NullClosure",
        "Pest\\TestSuite"
      ],
      "sorties": [
        "public func tion"
      ],
      "appelle": [
        "src/PendingCalls/Concerns/Describable.php",
        "src/Support/Closure.php"
      ],
      "est_appele_par": [],
      "type_noeud": "point_entree"
    },
    "src/PendingCalls/DescribeCall.php": {
      "fichier": "src/PendingCalls/DescribeCall.php",
      "langage": "php",
      "lignes": 86,
      "taille_bytes": 1842,
      "entrees": [
        "Closure",
        "Pest\\Support\\Backtrace",
        "Pest\\Support\\Description",
        "Pest\\TestSuite"
      ],
      "sorties": [
        "public func tion"
      ],
      "appelle": [
        "src/Support/Closure.php"
      ],
      "est_appele_par": [],
      "type_noeud": "standard"
    },
    "src/PendingCalls/AfterEachCall.php": {
      "fichier": "src/PendingCalls/AfterEachCall.php",
      "langage": "php",
      "lignes": 83,
      "taille_bytes": 2002,
      "entrees": [
        "Closure",
        "Describable",
        "Pest\\PendingCalls\\Concerns\\Describable",
        "Pest\\Support\\Arr",
        "Pest\\Support\\Backtrace",
        "Pest\\Support\\ChainableClosure",
        "Pest\\Support\\HigherOrderMessageCollection",
        "Pest\\Support\\NullClosure",
        "Pest\\TestSuite"
      ],
      "sorties": [
        "public func tion"
      ],
      "appelle": [
        "src/PendingCalls/Concerns/Describable.php",
        "src/Support/Closure.php"
      ],
      "est_appele_par": [],
      "type_noeud": "point_entree"
    },
    "src/PendingCalls/UsesCall.php": {
      "fichier": "src/PendingCalls/UsesCall.php",
      "langage": "php",
      "lignes": 183,
      "taille_bytes": 4176,
      "entrees": [
        "Closure",
        "NunoMaduro\\Collision\\Adapters\\Phpunit\\Printers\\DefaultPrinter",
        "Pest\\TestSuite"
      ],
      "sorties": [
        "public func tion"
      ],
      "appelle": [
        "src/Support/Closure.php"
      ],
      "est_appele_par": [],
      "type_noeud": "standard"
    },
    "src/PendingCalls/Concerns/Describable.php": {
      "fichier": "src/PendingCalls/Concerns/Describable.php",
      "langage": "php",
      "lignes": 25,
      "taille_bytes": 464,
      "entrees": [],
      "sorties": [
        "trait Describable"
      ],
      "appelle": [],
      "est_appele_par": [
        "src/PendingCalls/AfterEachCall.php",
        "src/PendingCalls/BeforeEachCall.php",
        "src/PendingCalls/TestCall.php"
      ],
      "type_noeud": "feuille"
    },
    "src/TestCases/IgnorableTestCase.php": {
      "fichier": "src/TestCases/IgnorableTestCase.php",
      "langage": "php",
      "lignes": 15,
      "taille_bytes": 176,
      "entrees": [
        "PHPUnit\\Framework\\TestCase"
      ],
      "sorties": [],
      "appelle": [],
      "est_appele_par": [],
      "type_noeud": "standard"
    },
    "src/Plugins/Init.php": {
      "fichier": "src/Plugins/Init.php",
      "langage": "php",
      "lignes": 124,
      "taille_bytes": 3058,
      "entrees": [
        "Composer\\InstalledVersions",
        "Pest\\Console\\Thanks",
        "Pest\\Contracts\\Plugins\\HandlesArguments",
        "Pest\\Support\\View",
        "Pest\\TestSuite",
        "Symfony\\Component\\Console\\Input\\InputInterface",
        "Symfony\\Component\\Console\\Output\\OutputInterface"
      ],
      "sorties": [
        "public func tion"
      ],
      "appelle": [],
      "est_appele_par": [],
      "type_noeud": "standard"
    },
    "src/Plugins/Memory.php": {
      "fichier": "src/Plugins/Memory.php",
      "langage": "php",
      "lignes": 56,
      "taille_bytes": 1162,
      "entrees": [
        "Concerns\\HandleArguments",
        "Pest\\Contracts\\Plugins\\AddsOutput",
        "Pest\\Contracts\\Plugins\\HandlesArguments",
        "Symfony\\Component\\Console\\Output\\OutputInterface"
      ],
      "sorties": [
        "public func tion"
      ],
      "appelle": [],
      "est_appele_par": [],
      "type_noeud": "standard"
    },
    "src/Plugins/Printer.php": {
      "fichier": "src/Plugins/Printer.php",
      "langage": "php",
      "lignes": 31,
      "taille_bytes": 591,
      "entrees": [
        "Concerns\\HandleArguments",
        "Pest\\Contracts\\Plugins\\HandlesArguments"
      ],
      "sorties": [
        "public func tion"
      ],
      "appelle": [],
      "est_appele_par": [],
      "type_noeud": "standard"
    },
    "src/Plugins/Only.php": {
      "fichier": "src/Plugins/Only.php",
      "langage": "php",
      "lignes": 101,
      "taille_bytes": 2302,
      "entrees": [
        "PHPUnit\\Framework\\Attributes\\Group",
        "Pest\\Contracts\\Plugins\\Terminable",
        "Pest\\Factories\\Attribute",
        "Pest\\Factories\\TestCaseMethodFactory",
        "Pest\\PendingCalls\\TestCall"
      ],
      "sorties": [
        "public func tion"
      ],
      "appelle": [],
      "est_appele_par": [],
      "type_noeud": "standard"
    },
    "src/Plugins/Parallel.php": {
      "fichier": "src/Plugins/Parallel.php",
      "langage": "php",
      "lignes": 200,
      "taille_bytes": 6030,
      "entrees": [
        "HandleArguments",
        "ParaTest\\ParaTestCommand",
        "Pest\\Contracts\\Plugins\\HandlesArguments",
        "Pest\\Plugins\\Actions\\CallsAddsOutput",
        "Pest\\Plugins\\Concerns\\HandleArguments",
        "Pest\\Plugins\\Parallel\\Contracts\\HandlersWorkerArguments",
        "Pest\\Plugins\\Parallel\\Paratest\\CleanConsoleOutput",
        "Pest\\Support\\Arr",
        "Pest\\Support\\Container",
        "Pest\\TestSuite",
        "Stringable",
        "Symfony\\Component\\Console\\Application",
        "Symfony\\Component\\Console\\Input\\ArgvInput",
        "function"
      ],
      "sorties": [
        "public func tion"
      ],
      "appelle": [
        "src/Plugins/Concerns/HandleArguments.php"
      ],
      "est_appele_par": [],
      "type_noeud": "standard"
    },
    "src/Plugins/Profile.php": {
      "fichier": "src/Plugins/Profile.php",
      "langage": "php",
      "lignes": 32,
      "taille_bytes": 664,
      "entrees": [
        "Concerns\\HandleArguments",
        "Pest\\Contracts\\Plugins\\HandlesArguments",
        "Pest\\Exceptions\\InvalidOption"
      ],
      "sorties": [
        "public func tion"
      ],
      "appelle": [],
      "est_appele_par": [],
      "type_noeud": "standard"
    },
    "src/Plugins/Verbose.php": {
      "fichier": "src/Plugins/Verbose.php",
      "langage": "php",
      "lignes": 38,
      "taille_bytes": 814,
      "entrees": [
        "Concerns\\HandleArguments",
        "Pest\\Contracts\\Plugins\\HandlesArguments"
      ],
      "sorties": [
        "public func tion"
      ],
      "appelle": [],
      "est_appele_par": [],
      "type_noeud": "standard"
    },
    "src/Plugins/Environment.php": {
      "fichier": "src/Plugins/Environment.php",
      "langage": "php",
      "lignes": 56,
      "taille_bytes": 1056,
      "entrees": [
        "Pest\\Contracts\\Plugins\\HandlesArguments"
      ],
      "sorties": [
        "public func tion"
      ],
      "appelle": [],
      "est_appele_par": [],
      "type_noeud": "standard"
    },
    "src/Plugins/Version.php": {
      "fichier": "src/Plugins/Version.php",
      "langage": "php",
      "lignes": 34,
      "taille_bytes": 586,
      "entrees": [
        "Concerns\\HandleArguments",
        "Pest\\Contracts\\Plugins\\HandlesArguments",
        "Pest\\Support\\View",
        "function"
      ],
      "sorties": [
        "public func tion"
      ],
      "appelle": [],
      "est_appele_par": [],
      "type_noeud": "standard"
    },
    "src/Plugins/ProcessIsolation.php": {
      "fichier": "src/Plugins/ProcessIsolation.php",
      "langage": "php",
      "lignes": 28,
      "taille_bytes": 564,
      "entrees": [
        "Concerns\\HandleArguments",
        "Pest\\Contracts\\Plugins\\HandlesArguments",
        "Pest\\Exceptions\\InvalidOption"
      ],
      "sorties": [
        "public func tion"
      ],
      "appelle": [],
      "est_appele_par": [],
      "type_noeud": "standard"
    },
    "src/Plugins/Cache.php": {
      "fichier": "src/Plugins/Cache.php",
      "langage": "php",
      "lignes": 59,
      "taille_bytes": 1787,
      "entrees": [
        "HandleArguments",
        "PHPUnit\\TextUI\\CliArguments\\Builder",
        "PHPUnit\\TextUI\\CliArguments\\XmlConfigurationFileFinder",
        "PHPUnit\\TextUI\\XmlConfiguration\\DefaultConfiguration",
        "PHPUnit\\TextUI\\XmlConfiguration\\Loader",
        "Pest\\Contracts\\Plugins\\HandlesArguments",
        "Pest\\Plugins\\Concerns\\HandleArguments"
      ],
      "sorties": [
        "public func tion"
      ],
      "appelle": [
        "src/Plugins/Concerns/HandleArguments.php"
      ],
      "est_appele_par": [],
      "type_noeud": "standard"
    },
    "src/Plugins/Coverage.php": {
      "fichier": "src/Plugins/Coverage.php",
      "langage": "php",
      "lignes": 184,
      "taille_bytes": 6072,
      "entrees": [
        "Pest\\Contracts\\Plugins\\AddsOutput",
        "Pest\\Contracts\\Plugins\\HandlesArguments",
        "Pest\\Support\\Str",
        "Symfony\\Component\\Console\\Input\\ArgvInput",
        "Symfony\\Component\\Console\\Input\\InputDefinition",
        "Symfony\\Component\\Console\\Input\\InputOption",
        "Symfony\\Component\\Console\\Output\\OutputInterface"
      ],
      "sorties": [
        "public func tion"
      ],
      "appelle": [],
      "est_appele_par": [],
      "type_noeud": "standard"
    },
    "src/Plugins/Configuration.php": {
      "fichier": "src/Plugins/Configuration.php",
      "langage": "php",
      "lignes": 96,
      "taille_bytes": 2460,
      "entrees": [
        "DOMDocument",
        "HandleArguments",
        "PHPUnit\\TextUI\\CliArguments\\Builder",
        "PHPUnit\\TextUI\\CliArguments\\XmlConfigurationFileFinder",
        "Pest\\Contracts\\Plugins\\HandlesArguments",
        "Pest\\Contracts\\Plugins\\Terminable",
        "Pest\\Plugins\\Concerns\\HandleArguments"
      ],
      "sorties": [
        "public func tion"
      ],
      "appelle": [
        "src/Plugins/Concerns/HandleArguments.php"
      ],
      "est_appele_par": [],
      "type_noeud": "standard"
    },
    "src/Plugins/Snapshot.php": {
      "fichier": "src/Plugins/Snapshot.php",
      "langage": "php",
      "lignes": 35,
      "taille_bytes": 800,
      "entrees": [
        "Concerns\\HandleArguments",
        "Pest\\Contracts\\Plugins\\HandlesArguments",
        "Pest\\Exceptions\\InvalidOption",
        "Pest\\TestSuite"
      ],
      "sorties": [
        "public func tion"
      ],
      "appelle": [],
      "est_appele_par": [],
      "type_noeud": "standard"
    },
    "src/Plugins/Retry.php": {
      "fichier": "src/Plugins/Retry.php",
      "langage": "php",
      "lignes": 36,
      "taille_bytes": 842,
      "entrees": [
        "Concerns\\HandleArguments",
        "Pest\\Contracts\\Plugins\\HandlesArguments",
        "Pest\\Exceptions\\InvalidOption"
      ],
      "sorties": [
        "public func tion"
      ],
      "appelle": [],
      "est_appele_par": [],
      "type_noeud": "standard"
    },
    "src/Plugins/Help.php": {
      "fichier": "src/Plugins/Help.php",
      "langage": "php",
      "lignes": 229,
      "taille_bytes": 7773,
      "entrees": [
        "Concerns\\HandleArguments",
        "PHPUnit\\TextUI\\Help",
        "Pest\\Contracts\\Plugins\\HandlesArguments",
        "Pest\\Support\\View",
        "Symfony\\Component\\Console\\Output\\OutputInterface",
        "function"
      ],
      "sorties": [
        "public func tion"
      ],
      "appelle": [],
      "est_appele_par": [],
      "type_noeud": "standard"
    },
    "src/Plugins/Shard.php": {
      "fichier": "src/Plugins/Shard.php",
      "langage": "php",
      "lignes": 177,
      "taille_bytes": 4848,
      "entrees": [
        "Concerns\\HandleArguments",
        "Pest\\Contracts\\Plugins\\AddsOutput",
        "Pest\\Contracts\\Plugins\\HandlesArguments",
        "Pest\\Exceptions\\InvalidOption",
        "Symfony\\Component\\Console\\Input\\ArgvInput",
        "Symfony\\Component\\Console\\Input\\InputInterface",
        "Symfony\\Component\\Console\\Output\\OutputInterface",
        "Symfony\\Component\\Process\\Process"
      ],
      "sorties": [
        "public func tion"
      ],
      "appelle": [],
      "est_appele_par": [],
      "type_noeud": "standard"
    },
    "src/Plugins/Bail.php": {
      "fichier": "src/Plugins/Bail.php",
      "langage": "php",
      "lignes": 31,
      "taille_bytes": 749,
      "entrees": [
        "HandleArguments",
        "Pest\\Contracts\\Plugins\\HandlesArguments",
        "Pest\\Plugins\\Concerns\\HandleArguments"
      ],
      "sorties": [
        "public func tion"
      ],
      "appelle": [
        "src/Plugins/Concerns/HandleArguments.php"
      ],
      "est_appele_par": [],
      "type_noeud": "standard"
    },
    "src/Plugins/Actions/CallsBoot.php": {
      "fichier": "src/Plugins/Actions/CallsBoot.php",
      "langage": "php",
      "lignes": 29,
      "taille_bytes": 524,
      "entrees": [
        "Pest\\Contracts\\Plugins",
        "Pest\\Plugin\\Loader"
      ],
      "sorties": [],
      "appelle": [],
      "est_appele_par": [],
      "type_noeud": "standard"
    },
    "src/Plugins/Actions/CallsHandleOriginalArguments.php": {
      "fichier": "src/Plugins/Actions/CallsHandleOriginalArguments.php",
      "langage": "php",
      "lignes": 31,
      "taille_bytes": 678,
      "entrees": [
        "Pest\\Contracts\\Plugins",
        "Pest\\Plugin\\Loader"
      ],
      "sorties": [],
      "appelle": [],
      "est_appele_par": [],
      "type_noeud": "standard"
    },
    "src/Plugins/Actions/CallsTerminable.php": {
      "fichier": "src/Plugins/Actions/CallsTerminable.php",
      "langage": "php",
      "lignes": 29,
      "taille_bytes": 544,
      "entrees": [
        "Pest\\Contracts\\Plugins",
        "Pest\\Plugin\\Loader"
      ],
      "sorties": [],
      "appelle": [],
      "est_appele_par": [],
      "type_noeud": "standard"
    },
    "src/Plugins/Actions/CallsAddsOutput.php": {
      "fichier": "src/Plugins/Actions/CallsAddsOutput.php",
      "langage": "php",
      "lignes": 31,
      "taille_bytes": 651,
      "entrees": [
        "Pest\\Contracts\\Plugins",
        "Pest\\Plugin\\Loader"
      ],
      "sorties": [],
      "appelle": [],
      "est_appele_par": [],
      "type_noeud": "standard"
    },
    "src/Plugins/Actions/CallsHandleArguments.php": {
      "fichier": "src/Plugins/Actions/CallsHandleArguments.php",
      "langage": "php",
      "lignes": 34,
      "taille_bytes": 712,
      "entrees": [
        "Pest\\Contracts\\Plugins",
        "Pest\\Plugin\\Loader"
      ],
      "sorties": [],
      "appelle": [],
      "est_appele_par": [],
      "type_noeud": "standard"
    },
    "src/Plugins/Parallel/Handlers/Parallel.php": {
      "fichier": "src/Plugins/Parallel/Handlers/Parallel.php",
      "langage": "php",
      "lignes": 37,
      "taille_bytes": 912,
      "entrees": [
        "HandleArguments",
        "Pest\\Contracts\\Plugins\\HandlesArguments",
        "Pest\\Plugins\\Concerns\\HandleArguments",
        "Pest\\Plugins\\Parallel\\Paratest\\WrapperRunner"
      ],
      "sorties": [
        "public func tion"
      ],
      "appelle": [
        "src/Plugins/Concerns/HandleArguments.php"
      ],
      "est_appele_par": [],
      "type_noeud": "standard"
    },
    "src/Plugins/Parallel/Handlers/Pest.php": {
      "fichier": "src/Plugins/Parallel/Handlers/Pest.php",
      "langage": "php",
      "lignes": 23,
      "taille_bytes": 529,
      "entrees": [
        "HandleArguments",
        "Pest\\Plugins\\Concerns\\HandleArguments",
        "Pest\\Plugins\\Parallel\\Contracts\\HandlersWorkerArguments"
      ],
      "sorties": [
        "public func tion"
      ],
      "appelle": [
        "src/Plugins/Concerns/HandleArguments.php"
      ],
      "est_appele_par": [],
      "type_noeud": "standard"
    },
    "src/Plugins/Parallel/Handlers/Laravel.php": {
      "fichier": "src/Plugins/Parallel/Handlers/Laravel.php",
      "langage": "php",
      "lignes": 106,
      "taille_bytes": 3063,
      "entrees": [
        "Closure",
        "Composer\\InstalledVersions",
        "HandleArguments",
        "Illuminate\\Testing\\ParallelRunner",
        "ParaTest\\Options",
        "ParaTest\\RunnerInterface",
        "Pest\\Contracts\\Plugins\\HandlesArguments",
        "Pest\\Plugins\\Concerns\\HandleArguments",
        "Pest\\Plugins\\Parallel\\Paratest\\WrapperRunner",
        "Symfony\\Component\\Console\\Output\\OutputInterface"
      ],
      "sorties": [
        "public func tion"
      ],
      "appelle": [
        "src/Plugins/Concerns/HandleArguments.php",
        "src/Support/Closure.php"
      ],
      "est_appele_par": [],
      "type_noeud": "point_entree"
    },
    "src/Plugins/Parallel/Support/CompactPrinter.php": {
      "fichier": "src/Plugins/Parallel/Support/CompactPrinter.php",
      "langage": "php",
      "lignes": 171,
      "taille_bytes": 4881,
      "entrees": [
        "NunoMaduro\\Collision\\Adapters\\Phpunit\\State",
        "NunoMaduro\\Collision\\Adapters\\Phpunit\\Style",
        "PHPUnit\\Event\\Telemetry\\GarbageCollectorStatus",
        "PHPUnit\\Event\\Telemetry\\HRTime",
        "PHPUnit\\Event\\Telemetry\\Info",
        "PHPUnit\\Event\\Telemetry\\MemoryUsage",
        "PHPUnit\\Event\\Telemetry\\Snapshot",
        "PHPUnit\\TestRunner\\TestResult\\TestResult",
        "ParaTest\\Options",
        "SebastianBergmann\\Timer\\Duration",
        "Symfony\\Component\\Console\\Output\\ConsoleOutput",
        "Symfony\\Component\\Console\\Output\\OutputInterface",
        "Termwind\\Terminal",
        "function"
      ],
      "sorties": [
        "public func tion"
      ],
      "appelle": [],
      "est_appele_par": [],
      "type_noeud": "standard"
    },
    "src/Plugins/Parallel/Paratest/WrapperRunner.php": {
      "fichier": "src/Plugins/Parallel/Paratest/WrapperRunner.php",
      "langage": "php",
      "lignes": 498,
      "taille_bytes": 17344,
      "entrees": [
        "NunoMaduro\\Collision\\Adapters\\Phpunit\\Support\\ResultReflection",
        "PHPUnit\\Event\\Facade",
        "PHPUnit\\Event\\TestRunner\\WarningTriggered",
        "PHPUnit\\Event\\Test\\AfterLastTestMethodFailed",
        "PHPUnit\\Runner\\CodeCoverage",
        "PHPUnit\\Runner\\ResultCache\\DefaultResultCache",
        "PHPUnit\\TestRunner\\TestResult\\Facade",
        "PHPUnit\\TestRunner\\TestResult\\TestResult",
        "PHPUnit\\TextUI\\Configuration\\CodeCoverageFilterRegistry",
        "PHPUnit\\Util\\ExcludeList",
        "ParaTest\\Coverage\\CoverageMerger",
        "ParaTest\\JUnit\\LogMerger",
        "ParaTest\\JUnit\\Writer",
        "ParaTest\\Options",
        "ParaTest\\RunnerInterface",
        "ParaTest\\WrapperRunner\\SuiteLoader",
        "ParaTest\\WrapperRunner\\WrapperWorker",
        "Pest\\Result",
        "Pest\\TestSuite",
        "SebastianBergmann\\Timer\\Timer",
        "SplFileInfo",
        "Symfony\\Component\\Console\\Output\\OutputInterface",
        "Symfony\\Component\\Process\\PhpExecutableFinder",
        "const",
        "function"
      ],
      "sorties": [
        "public func tion"
      ],
      "appelle": [],
      "est_appele_par": [],
      "type_noeud": "standard"
    },
    "src/Plugins/Parallel/Paratest/ResultPrinter.php": {
      "fichier": "src/Plugins/Parallel/Paratest/ResultPrinter.php",
      "langage": "php",
      "lignes": 235,
      "taille_bytes": 6444,
      "entrees": [
        "PHPUnit\\TestRunner\\TestResult\\TestResult",
        "PHPUnit\\TextUI\\Output\\Printer",
        "ParaTest\\Options",
        "Pest\\Plugins\\Parallel\\Support\\CompactPrinter",
        "Pest\\Support\\StateGenerator",
        "SebastianBergmann\\Timer\\Duration",
        "SplFileInfo",
        "Symfony\\Component\\Console\\Formatter\\OutputFormatter",
        "Symfony\\Component\\Console\\Output\\OutputInterface",
        "function"
      ],
      "sorties": [
        "public func tion"
      ],
      "appelle": [],
      "est_appele_par": [],
      "type_noeud": "standard"
    },
    "src/Plugins/Parallel/Paratest/CleanConsoleOutput.php": {
      "fichier": "src/Plugins/Parallel/Paratest/CleanConsoleOutput.php",
      "langage": "php",
      "lignes": 31,
      "taille_bytes": 704,
      "entrees": [
        "Symfony\\Component\\Console\\Output\\ConsoleOutput"
      ],
      "sorties": [],
      "appelle": [],
      "est_appele_par": [],
      "type_noeud": "standard"
    },
    "src/Plugins/Parallel/Contracts/HandlersWorkerArguments.php": {
      "fichier": "src/Plugins/Parallel/Contracts/HandlersWorkerArguments.php",
      "langage": "php",
      "lignes": 14,
      "taille_bytes": 279,
      "entrees": [],
      "sorties": [
        "interface HandlersWorkerArguments",
        "public func tion"
      ],
      "appelle": [],
      "est_appele_par": [],
      "type_noeud": "standard"
    },
    "src/Plugins/Concerns/HandleArguments.php": {
      "fichier": "src/Plugins/Concerns/HandleArguments.php",
      "langage": "php",
      "lignes": 59,
      "taille_bytes": 1316,
      "entrees": [],
      "sorties": [
        "public func tion",
        "trait HandleArguments"
      ],
      "appelle": [],
      "est_appele_par": [
        "src/Plugins/Bail.php",
        "src/Plugins/Cache.php",
        "src/Plugins/Configuration.php",
        "src/Plugins/Parallel.php",
        "src/Plugins/Parallel/Handlers/Laravel.php",
        "src/Plugins/Parallel/Handlers/Parallel.php",
        "src/Plugins/Parallel/Handlers/Pest.php"
      ],
      "type_noeud": "feuille"
    },
    "src/Console/Thanks.php": {
      "fichier": "src/Console/Thanks.php",
      "langage": "php",
      "lignes": 90,
      "taille_bytes": 2636,
      "entrees": [
        "Pest\\Bootstrappers\\BootView",
        "Pest\\Support\\View",
        "Symfony\\Component\\Console\\Helper\\SymfonyQuestionHelper",
        "Symfony\\Component\\Console\\Input\\ArrayInput",
        "Symfony\\Component\\Console\\Input\\InputInterface",
        "Symfony\\Component\\Console\\Output\\OutputInterface",
        "Symfony\\Component\\Console\\Question\\ConfirmationQuestion"
      ],
      "sorties": [
        "public func tion"
      ],
      "appelle": [],
      "est_appele_par": [],
      "type_noeud": "standard"
    },
    "src/Console/Help.php": {
      "fichier": "src/Console/Help.php",
      "langage": "php",
      "lignes": 44,
      "taille_bytes": 1149,
      "entrees": [
        "Symfony\\Component\\Console\\Output\\OutputInterface"
      ],
      "sorties": [
        "public func tion"
      ],
      "appelle": [],
      "est_appele_par": [],
      "type_noeud": "standard"
    },
    "src/Mixins/Expectation.php": {
      "fichier": "src/Mixins/Expectation.php",
      "langage": "php",
      "lignes": 1174,
      "taille_bytes": 31157,
      "entrees": [
        "BadMethodCallException",
        "Closure",
        "Countable",
        "DateTimeInterface",
        "Error",
        "InvalidArgumentException",
        "JsonSerializable",
        "PHPUnit\\Framework\\Assert",
        "PHPUnit\\Framework\\Constraint\\Constraint",
        "PHPUnit\\Framework\\ExpectationFailedException",
        "PHPUnit\\Framework\\TestCase",
        "Pest\\Exceptions\\InvalidExpectationValue",
        "Pest\\Matchers\\Any",
        "Pest\\Support\\Arr",
        "Pest\\Support\\Exporter",
        "Pest\\Support\\NullClosure",
        "Pest\\Support\\Str",
        "Pest\\TestSuite",
        "ReflectionFunction",
        "ReflectionNamedType",
        "Throwable",
        "Traversable"
      ],
      "sorties": [
        "public func tion"
      ],
      "appelle": [
        "src/Support/Closure.php"
      ],
      "est_appele_par": [],
      "type_noeud": "standard"
    },
    "src/Repositories/AfterEachRepository.php": {
      "fichier": "src/Repositories/AfterEachRepository.php",
      "langage": "php",
      "lignes": 58,
      "taille_bytes": 1517,
      "entrees": [
        "Closure",
        "Mockery",
        "Pest\\PendingCalls\\AfterEachCall",
        "Pest\\Support\\ChainableClosure",
        "Pest\\Support\\NullClosure"
      ],
      "sorties": [
        "public func tion"
      ],
      "appelle": [
        "src/Support/Closure.php"
      ],
      "est_appele_par": [],
      "type_noeud": "standard"
    },
    "src/Repositories/DatasetsRepository.php": {
      "fichier": "src/Repositories/DatasetsRepository.php",
      "langage": "php",
      "lignes": 240,
      "taille_bytes": 7197,
      "entrees": [
        "Closure",
        "Generator",
        "Pest\\Exceptions\\DatasetAlreadyExists",
        "Pest\\Exceptions\\DatasetDoesNotExist",
        "Pest\\Exceptions\\ShouldNotHappen",
        "Pest\\Support\\Exporter",
        "Traversable",
        "function"
      ],
      "sorties": [],
      "appelle": [
        "src/Support/Closure.php"
      ],
      "est_appele_par": [],
      "type_noeud": "standard"
    },
    "src/Repositories/TestRepository.php": {
      "fichier": "src/Repositories/TestRepository.php",
      "langage": "php",
      "lignes": 212,
      "taille_bytes": 6410,
      "entrees": [
        "Closure",
        "PHPUnit\\Framework\\Attributes\\Group",
        "PHPUnit\\Framework\\TestCase",
        "Pest\\Contracts\\TestCaseFilter",
        "Pest\\Contracts\\TestCaseMethodFilter",
        "Pest\\Exceptions\\TestCaseAlreadyInUse",
        "Pest\\Exceptions\\TestCaseClassOrTraitNotFound",
        "Pest\\Factories\\Attribute",
        "Pest\\Factories\\TestCaseFactory",
        "Pest\\Factories\\TestCaseMethodFactory",
        "Pest\\Support\\Str"
      ],
      "sorties": [
        "public func tion"
      ],
      "appelle": [
        "src/Support/Closure.php"
      ],
      "est_appele_par": [],
      "type_noeud": "standard"
    },
    "src/Repositories/SnapshotRepository.php": {
      "fichier": "src/Repositories/SnapshotRepository.php",
      "langage": "php",
      "lignes": 153,
      "taille_bytes": 4363,
      "entrees": [
        "Pest\\Exceptions\\ShouldNotHappen",
        "Pest\\TestSuite"
      ],
      "sorties": [
        "public func tion"
      ],
      "appelle": [],
      "est_appele_par": [],
      "type_noeud": "standard"
    },
    "src/Repositories/BeforeEachRepository.php": {
      "fichier": "src/Repositories/BeforeEachRepository.php",
      "langage": "php",
      "lignes": 52,
      "taille_bytes": 1471,
      "entrees": [
        "Closure",
        "Pest\\PendingCalls\\BeforeEachCall",
        "Pest\\Support\\ChainableClosure",
        "Pest\\Support\\NullClosure"
      ],
      "sorties": [
        "public func tion"
      ],
      "appelle": [
        "src/Support/Closure.php"
      ],
      "est_appele_par": [],
      "type_noeud": "standard"
    },
    "src/Repositories/BeforeAllRepository.php": {
      "fichier": "src/Repositories/BeforeAllRepository.php",
      "langage": "php",
      "lignes": 55,
      "taille_bytes": 1125,
      "entrees": [
        "Closure",
        "Pest\\Exceptions\\BeforeAllAlreadyExist",
        "Pest\\Support\\NullClosure",
        "Pest\\Support\\Reflection"
      ],
      "sorties": [
        "public func tion"
      ],
      "appelle": [
        "src/Support/Closure.php"
      ],
      "est_appele_par": [],
      "type_noeud": "standard"
    },
    "src/Repositories/AfterAllRepository.php": {
      "fichier": "src/Repositories/AfterAllRepository.php",
      "langage": "php",
      "lignes": 53,
      "taille_bytes": 1094,
      "entrees": [
        "Closure",
        "Pest\\Exceptions\\AfterAllAlreadyExist",
        "Pest\\Support\\NullClosure",
        "Pest\\Support\\Reflection"
      ],
      "sorties": [
        "public func tion"
      ],
      "appelle": [
        "src/Support/Closure.php"
      ],
      "est_appele_par": [],
      "type_noeud": "standard"
    },
    "src/Installers/PluginBrowser.php": {
      "fichier": "src/Installers/PluginBrowser.php",
      "langage": "php",
      "lignes": 15,
      "taille_bytes": 230,
      "entrees": [
        "Pest\\Support\\View"
      ],
      "sorties": [],
      "appelle": [],
      "est_appele_par": [],
      "type_noeud": "standard"
    },
    "src/Matchers/Any.php": {
      "fichier": "src/Matchers/Any.php",
      "langage": "php",
      "lignes": 10,
      "taille_bytes": 99,
      "entrees": [],
      "sorties": [],
      "appelle": [],
      "est_appele_par": [],
      "type_noeud": "standard"
    },
    "src/Support/ChainableClosure.php": {
      "fichier": "src/Support/ChainableClosure.php",
      "langage": "php",
      "lignes": 67,
      "taille_bytes": 2263,
      "entrees": [
        "Closure",
        "Pest\\Exceptions\\ShouldNotHappen"
      ],
      "sorties": [],
      "appelle": [
        "src/Support/Closure.php"
      ],
      "est_appele_par": [],
      "type_noeud": "standard"
    },
    "src/Support/Container.php": {
      "fichier": "src/Support/Container.php",
      "langage": "php",
      "lignes": 106,
      "taille_bytes": 2862,
      "entrees": [
        "Pest\\Exceptions\\ShouldNotHappen",
        "ReflectionClass",
        "ReflectionParameter"
      ],
      "sorties": [
        "public func tion"
      ],
      "appelle": [],
      "est_appele_par": [],
      "type_noeud": "standard"
    },
    "src/Support/DatasetInfo.php": {
      "fichier": "src/Support/DatasetInfo.php",
      "langage": "php",
      "lignes": 44,
      "taille_bytes": 945,
      "entrees": [
        "function"
      ],
      "sorties": [],
      "appelle": [],
      "est_appele_par": [],
      "type_noeud": "standard"
    },
    "src/Support/HigherOrderCallables.php": {
      "fichier": "src/Support/HigherOrderCallables.php",
      "langage": "php",
      "lignes": 62,
      "taille_bytes": 1436,
      "entrees": [
        "Closure",
        "Pest\\Expectation"
      ],
      "sorties": [
        "public func tion"
      ],
      "appelle": [
        "src/Support/Closure.php"
      ],
      "est_appele_par": [],
      "type_noeud": "standard"
    },
    "src/Support/Str.php": {
      "fichier": "src/Support/Str.php",
      "langage": "php",
      "lignes": 130,
      "taille_bytes": 3647,
      "entrees": [],
      "sorties": [],
      "appelle": [],
      "est_appele_par": [],
      "type_noeud": "standard"
    },
    "src/Support/ExceptionTrace.php": {
      "fichier": "src/Support/ExceptionTrace.php",
      "langage": "php",
      "lignes": 43,
      "taille_bytes": 1373,
      "entrees": [
        "Closure",
        "PHPUnit\\Framework\\TestCase",
        "Throwable"
      ],
      "sorties": [],
      "appelle": [
        "src/Support/Closure.php"
      ],
      "est_appele_par": [],
      "type_noeud": "standard"
    },
    "src/Support/Closure.php": {
      "fichier": "src/Support/Closure.php",
      "langage": "php",
      "lignes": 35,
      "taille_bytes": 815,
      "entrees": [
        "Closure",
        "Pest\\Exceptions\\ShouldNotHappen"
      ],
      "sorties": [],
      "appelle": [],
      "est_appele_par": [
        "src/ArchPresets/Custom.php",
        "src/Expectation.php",
        "src/Expectations/HigherOrderExpectation.php",
        "src/Factories/TestCaseMethodFactory.php",
        "src/Mixins/Expectation.php",
        "src/PendingCalls/AfterEachCall.php",
        "src/PendingCalls/BeforeEachCall.php",
        "src/PendingCalls/DescribeCall.php",
        "src/PendingCalls/TestCall.php",
        "src/PendingCalls/UsesCall.php",
        "src/Plugins/Parallel/Handlers/Laravel.php",
        "src/Preset.php",
        "src/Repositories/AfterAllRepository.php",
        "src/Repositories/AfterEachRepository.php",
        "src/Repositories/BeforeAllRepository.php",
        "src/Repositories/BeforeEachRepository.php",
        "src/Repositories/DatasetsRepository.php",
        "src/Repositories/TestRepository.php",
        "src/Support/ChainableClosure.php",
        "src/Support/ExceptionTrace.php",
        "src/Support/HigherOrderCallables.php",
        "src/Support/Reflection.php"
      ],
      "type_noeud": "feuille"
    },
    "src/Support/Reflection.php": {
      "fichier": "src/Support/Reflection.php",
      "langage": "php",
      "lignes": 281,
      "taille_bytes": 9338,
      "entrees": [
        "Closure",
        "InvalidArgumentException",
        "Pest\\Exceptions\\ShouldNotHappen",
        "Pest\\TestSuite",
        "ReflectionClass",
        "ReflectionException",
        "ReflectionFunction",
        "ReflectionMethod",
        "ReflectionNamedType",
        "ReflectionParameter",
        "ReflectionProperty",
        "ReflectionUnionType"
      ],
      "sorties": [],
      "appelle": [
        "src/Support/Closure.php"
      ],
      "est_appele_par": [],
      "type_noeud": "standard"
    }
  },
  "edges": [
    {
      "de": "src/Preset.php",
      "vers": "src/Support/Closure.php",
      "type": "interne"
    },
    {
      "de": "src/Expectation.php",
      "vers": "src/Factories/Attribute.php",
      "type": "interne"
    },
    {
      "de": "src/Expectation.php",
      "vers": "src/Support/Closure.php",
      "type": "interne"
    },
    {
      "de": "src/Expectations/HigherOrderExpectation.php",
      "vers": "src/Support/Closure.php",
      "type": "interne"
    },
    {
      "de": "src/Expectations/OppositeExpectation.php",
      "vers": "src/Factories/Attribute.php",
      "type": "interne"
    },
    {
      "de": "src/ArchPresets/Custom.php",
      "vers": "src/Support/Closure.php",
      "type": "interne"
    },
    {
      "de": "src/Factories/TestCaseFactory.php",
      "vers": "src/Factories/Concerns/HigherOrderable.php",
      "type": "interne"
    },
    {
      "de": "src/Factories/TestCaseMethodFactory.php",
      "vers": "src/Factories/Concerns/HigherOrderable.php",
      "type": "interne"
    },
    {
      "de": "src/Factories/TestCaseMethodFactory.php",
      "vers": "src/Support/Closure.php",
      "type": "interne"
    },
    {
      "de": "src/PendingCalls/TestCall.php",
      "vers": "src/PendingCalls/Concerns/Describable.php",
      "type": "interne"
    },
    {
      "de": "src/PendingCalls/TestCall.php",
      "vers": "src/Support/Closure.php",
      "type": "interne"
    },
    {
      "de": "src/PendingCalls/BeforeEachCall.php",
      "vers": "src/PendingCalls/Concerns/Describable.php",
      "type": "interne"
    },
    {
      "de": "src/PendingCalls/BeforeEachCall.php",
      "vers": "src/Support/Closure.php",
      "type": "interne"
    },
    {
      "de": "src/PendingCalls/DescribeCall.php",
      "vers": "src/Support/Closure.php",
      "type": "interne"
    },
    {
      "de": "src/PendingCalls/AfterEachCall.php",
      "vers": "src/PendingCalls/Concerns/Describable.php",
      "type": "interne"
    },
    {
      "de": "src/PendingCalls/AfterEachCall.php",
      "vers": "src/Support/Closure.php",
      "type": "interne"
    },
    {
      "de": "src/PendingCalls/UsesCall.php",
      "vers": "src/Support/Closure.php",
      "type": "interne"
    },
    {
      "de": "src/Plugins/Parallel.php",
      "vers": "src/Plugins/Concerns/HandleArguments.php",
      "type": "interne"
    },
    {
      "de": "src/Plugins/Cache.php",
      "vers": "src/Plugins/Concerns/HandleArguments.php",
      "type": "interne"
    },
    {
      "de": "src/Plugins/Configuration.php",
      "vers": "src/Plugins/Concerns/HandleArguments.php",
      "type": "interne"
    },
    {
      "de": "src/Plugins/Bail.php",
      "vers": "src/Plugins/Concerns/HandleArguments.php",
      "type": "interne"
    },
    {
      "de": "src/Plugins/Parallel/Handlers/Parallel.php",
      "vers": "src/Plugins/Concerns/HandleArguments.php",
      "type": "interne"
    },
    {
      "de": "src/Plugins/Parallel/Handlers/Pest.php",
      "vers": "src/Plugins/Concerns/HandleArguments.php",
      "type": "interne"
    },
    {
      "de": "src/Plugins/Parallel/Handlers/Laravel.php",
      "vers": "src/Plugins/Concerns/HandleArguments.php",
      "type": "interne"
    },
    {
      "de": "src/Plugins/Parallel/Handlers/Laravel.php",
      "vers": "src/Support/Closure.php",
      "type": "interne"
    },
    {
      "de": "src/Mixins/Expectation.php",
      "vers": "src/Support/Closure.php",
      "type": "interne"
    },
    {
      "de": "src/Repositories/AfterEachRepository.php",
      "vers": "src/Support/Closure.php",
      "type": "interne"
    },
    {
      "de": "src/Repositories/DatasetsRepository.php",
      "vers": "src/Support/Closure.php",
      "type": "interne"
    },
    {
      "de": "src/Repositories/TestRepository.php",
      "vers": "src/Support/Closure.php",
      "type": "interne"
    },
    {
      "de": "src/Repositories/BeforeEachRepository.php",
      "vers": "src/Support/Closure.php",
      "type": "interne"
    },
    {
      "de": "src/Repositories/BeforeAllRepository.php",
      "vers": "src/Support/Closure.php",
      "type": "interne"
    },
    {
      "de": "src/Repositories/AfterAllRepository.php",
      "vers": "src/Support/Closure.php",
      "type": "interne"
    },
    {
      "de": "src/Support/ChainableClosure.php",
      "vers": "src/Support/Closure.php",
      "type": "interne"
    },
    {
      "de": "src/Support/HigherOrderCallables.php",
      "vers": "src/Support/Closure.php",
      "type": "interne"
    },
    {
      "de": "src/Support/ExceptionTrace.php",
      "vers": "src/Support/Closure.php",
      "type": "interne"
    },
    {
      "de": "src/Support/Reflection.php",
      "vers": "src/Support/Closure.php",
      "type": "interne"
    }
  ],
  "patterns": [
    "point_entree → 'src/Expectation.php'",
    "point_entree → 'src/Factories/TestCaseMethodFactory.php'",
    "point_entree → 'src/PendingCalls/TestCall.php'",
    "point_entree → 'src/PendingCalls/BeforeEachCall.php'",
    "point_entree → 'src/PendingCalls/AfterEachCall.php'",
    "feuille → 'src/PendingCalls/Concerns/Describable.php' (in=3)",
    "point_entree → 'src/Plugins/Parallel/Handlers/Laravel.php'",
    "feuille → 'src/Plugins/Concerns/HandleArguments.php' (in=7)",
    "feuille → 'src/Support/Closure.php' (in=22)"
  ]
}