{
  "meta": {
    "projet": "compojure",
    "schema": "universal-graph-extractor v3.0",
    "langages": {
      "clojure": 12,
      "html": 1
    }
  },
  "stats": {
    "fichiers_total": 13,
    "edges_total": 0,
    "edges_circulaires": 0,
    "noeuds_centraux": 0,
    "noeuds_feuilles": 0,
    "noeuds_hubs": 0,
    "points_entree": 0,
    "fichier_plus_appele": "project.clj"
  },
  "noeuds": {
    "project.clj": {
      "fichier": "project.clj",
      "langage": "clojure",
      "lignes": 26,
      "taille_bytes": 1153,
      "entrees": [],
      "sorties": [],
      "appelle": [],
      "est_appele_par": [],
      "type_noeud": "standard"
    },
    "test/test_files/index.html": {
      "fichier": "test/test_files/index.html",
      "langage": "html",
      "lignes": 1,
      "taille_bytes": 31,
      "entrees": [],
      "sorties": [],
      "appelle": [],
      "est_appele_par": [],
      "type_noeud": "standard"
    },
    "test/compojure/response_test.clj": {
      "fichier": "test/compojure/response_test.clj",
      "langage": "clojure",
      "lignes": 97,
      "taille_bytes": 3603,
      "entrees": [],
      "sorties": [],
      "appelle": [],
      "est_appele_par": [],
      "type_noeud": "standard"
    },
    "test/compojure/core_test.clj": {
      "fichier": "test/compojure/core_test.clj",
      "langage": "clojure",
      "lignes": 482,
      "taille_bytes": 18538,
      "entrees": [],
      "sorties": [],
      "appelle": [],
      "est_appele_par": [],
      "type_noeud": "standard"
    },
    "test/compojure/middleware_test.clj": {
      "fichier": "test/compojure/middleware_test.clj",
      "langage": "clojure",
      "lignes": 52,
      "taille_bytes": 1941,
      "entrees": [],
      "sorties": [],
      "appelle": [],
      "est_appele_par": [],
      "type_noeud": "standard"
    },
    "test/compojure/coercions_test.clj": {
      "fichier": "test/compojure/coercions_test.clj",
      "langage": "clojure",
      "lignes": 22,
      "taille_bytes": 737,
      "entrees": [],
      "sorties": [],
      "appelle": [],
      "est_appele_par": [],
      "type_noeud": "standard"
    },
    "test/compojure/route_test.clj": {
      "fichier": "test/compojure/route_test.clj",
      "langage": "clojure",
      "lignes": 72,
      "taille_bytes": 2932,
      "entrees": [],
      "sorties": [],
      "appelle": [],
      "est_appele_par": [],
      "type_noeud": "standard"
    },
    "src/compojure/middleware.clj": {
      "fichier": "src/compojure/middleware.clj",
      "langage": "clojure",
      "lignes": 41,
      "taille_bytes": 1584,
      "entrees": [],
      "sorties": [],
      "appelle": [],
      "est_appele_par": [],
      "type_noeud": "standard"
    },
    "src/compojure/coercions.clj": {
      "fichier": "src/compojure/coercions.clj",
      "langage": "clojure",
      "lignes": 20,
      "taille_bytes": 592,
      "entrees": [],
      "sorties": [],
      "appelle": [],
      "est_appele_par": [],
      "type_noeud": "standard"
    },
    "src/compojure/response.clj": {
      "fichier": "src/compojure/response.clj",
      "langage": "clojure",
      "lignes": 73,
      "taille_bytes": 2440,
      "entrees": [],
      "sorties": [],
      "appelle": [],
      "est_appele_par": [],
      "type_noeud": "standard"
    },
    "src/compojure/core.clj": {
      "fichier": "src/compojure/core.clj",
      "langage": "clojure",
      "lignes": 357,
      "taille_bytes": 11743,
      "entrees": [],
      "sorties": [],
      "appelle": [],
      "est_appele_par": [],
      "type_noeud": "standard"
    },
    "src/compojure/route.clj": {
      "fichier": "src/compojure/route.clj",
      "langage": "clojure",
      "lignes": 65,
      "taille_bytes": 2135,
      "entrees": [],
      "sorties": [],
      "appelle": [],
      "est_appele_par": [],
      "type_noeud": "standard"
    },
    "src/compojure/handler.clj": {
      "fichier": "src/compojure/handler.clj",
      "langage": "clojure",
      "lignes": 61,
      "taille_bytes": 1569,
      "entrees": [],
      "sorties": [],
      "appelle": [],
      "est_appele_par": [],
      "type_noeud": "standard"
    }
  },
  "edges": [],
  "patterns": []
}